setup.py
./src/__init__.py
./src/funcDetec.py
rattler_func_detection.egg-info/PKG-INFO
rattler_func_detection.egg-info/SOURCES.txt
rattler_func_detection.egg-info/dependency_links.txt
rattler_func_detection.egg-info/entry_points.txt
rattler_func_detection.egg-info/not-zip-safe
rattler_func_detection.egg-info/requires.txt
rattler_func_detection.egg-info/top_level.txt
src/__init__.py
src/funcDetec.py