Metadata-Version: 1.1
Name: rattler-func-detection
Version: 1.0.1
Summary: This is a tool for function collision detect
Home-page: https://github.com/airfer/rattler
Author: wangyukun
Author-email: airfer@126.com
License: GPLv3
Keywords: collision rattler-func-detec
Platform: UNKNOWN
Classifier: Development Status :: 3 - Alpha
Classifier: Topic :: Utilities
Classifier: License :: OSI Approved :: GNU General Public License (GPL)
